easy_data_explorer/__init__.py
easy_data_explorer/easy_data_explorer.py
easy_data_explorer_amandeepfj-0.0.5.dist-info/LICENSE
easy_data_explorer_amandeepfj-0.0.5.dist-info/METADATA
easy_data_explorer_amandeepfj-0.0.5.dist-info/WHEEL
easy_data_explorer_amandeepfj-0.0.5.dist-info/top_level.txt
easy_data_explorer_amandeepfj-0.0.5.dist-info/RECORD
