Metadata-Version: 2.1
Name: easy-data-explorer-amandeepfj
Version: 0.0.5
Summary: Easy Data Explorer
Home-page: https://github.com/amandeepfj/easy_data_explorer
Author: amandeepfj (Amandeep Jiddewar)
Author-email: <amandeep.jiddewar@alumni.emory.edu>
License: UNKNOWN
Project-URL: Bug Tracker, https://github.com/amandeepfj/easy_data_explorer/issues
Keywords: python,data explore
Platform: UNKNOWN
Classifier: Development Status :: 1 - Planning
Classifier: Intended Audience :: Developers
Classifier: Programming Language :: Python :: 3
Classifier: Operating System :: OS Independent
Requires-Python: >=3.6
License-File: LICENSE
Requires-Dist: pandas
Requires-Dist: numpy
Requires-Dist: matplotlib
Requires-Dist: seaborn
Requires-Dist: pydataset
